image_packed_blur_kakasw/__init__.py
image_packed_blur_kakasw/filters.py
image_packed_blur_kakasw/transformations.py
image_packed_blur_kakasw/utils.py
image_processing/__init__.py
image_processing/filters.py
image_processing/transformations.py
image_processing/utils.py
image_packed_blur_kakasw-0.2.1.dist-info/METADATA
image_packed_blur_kakasw-0.2.1.dist-info/WHEEL
image_packed_blur_kakasw-0.2.1.dist-info/top_level.txt
image_packed_blur_kakasw-0.2.1.dist-info/RECORD
